[{"name":"MedCPU","href":"http://ehr.softwareinsider.com/l/1024/MedCPU"},{"name":"E-Z BIS","href":"http://ehr.softwareinsider.com/l/1026/E-Z-BIS"},{"name":"myUABMedicine","href":"http://ehr.softwareinsider.com/l/1028/myUABMedicine"},{"name":"Indian Health Service","href":"http://ehr.softwareinsider.com/l/1030/Indian-Health-Service"},{"name":"Dignity Health","href":"http://ehr.softwareinsider.com/l/1031/Dignity-Health"},{"name":"US Oncology","href":"http://ehr.softwareinsider.com/l/1034/US-Oncology"},{"name":"Shareable Ink","href":"http://ehr.softwareinsider.com/l/1036/Shareable-Ink"},{"name":"Williams Group","href":"http://ehr.softwareinsider.com/l/1040/Williams-Group"},{"name":"tgi Software","href":"http://ehr.softwareinsider.com/l/1042/tgi-Software"},{"name":"Chart Talk","href":"http://ehr.softwareinsider.com/l/1043/Chart-Talk"}]