[{"name":"SEOmetrics","href":"http://seo.softwareinsider.com/l/34/SEOmetrics"},{"name":"iSpionage","href":"http://seo.softwareinsider.com/l/35/iSpionage"},{"name":"PlagSpotter","href":"http://seo.softwareinsider.com/l/38/PlagSpotter"},{"name":"Mozcheck.com","href":"http://seo.softwareinsider.com/l/39/Mozcheck-com"},{"name":"Keyword Potential Estimator","href":"http://seo.softwareinsider.com/l/41/Keyword-Potential-Estimator"},{"name":"Online SEO Analyzer","href":"http://seo.softwareinsider.com/l/42/Online-SEO-Analyzer"},{"name":"IPullRank","href":"http://seo.softwareinsider.com/l/43/IPullRank"},{"name":"AddMe.com","href":"http://seo.softwareinsider.com/l/46/AddMe-com"},{"name":"Raven Tools","href":"http://seo.softwareinsider.com/l/49/Raven-Tools"},{"name":"AuthorityLabs","href":"http://seo.softwareinsider.com/l/50/AuthorityLabs"}]