[{"name":"AMT","href":"http://distribution.softwareinsider.com/l/136/AMT"},{"name":"Collect WMS","href":"http://distribution.softwareinsider.com/l/140/Collect-WMS"},{"name":"DCMS Warehouse Management System","href":"http://distribution.softwareinsider.com/l/141/DCMS-Warehouse-Management-System"},{"name":"Produce Pro","href":"http://distribution.softwareinsider.com/l/142/Produce-Pro"},{"name":"Anywhere Warehouse Management","href":"http://distribution.softwareinsider.com/l/145/Anywhere-Warehouse-Management"},{"name":"Step","href":"http://distribution.softwareinsider.com/l/149/Step"},{"name":"Ceritar Suite","href":"http://distribution.softwareinsider.com/l/152/Ceritar-Suite"},{"name":"Plus & Minus","href":"http://distribution.softwareinsider.com/l/154/Plus-And-Minus"},{"name":"Common Sense","href":"http://distribution.softwareinsider.com/l/157/Common-Sense"},{"name":"Pentagon 2000SQL","href":"http://distribution.softwareinsider.com/l/159/Pentagon-2000SQL"}]